{
  "total": {
    "inputTokens": 195852,
    "outputTokens": 15827,
    "totalTokens": 2267615,
    "estimatedCost": 0.12958,
    "sessionCount": 3
  },
  "daily": {
    "2026-03-11": {
      "inputTokens": 34853,
      "outputTokens": 4211,
      "totalTokens": 290200,
      "sessionCount": 1,
      "cost": 0.025848500000000003
    },
    "2026-03-16": {
      "inputTokens": 145337,
      "outputTokens": 10580,
      "totalTokens": 1869581,
      "sessionCount": 1,
      "cost": 0.0938285
    },
    "2026-03-17": {
      "inputTokens": 15662,
      "outputTokens": 1036,
      "totalTokens": 107834,
      "sessionCount": 1,
      "cost": 0.009902999999999999
    }
  },
  "sessions": [
    {
      "file": "ba74aea2-70b9-42bd-a7d4-b17060836a8a.jsonl",
      "date": "2026-03-11",
      "inputTokens": 34853,
      "outputTokens": 4211,
      "totalTokens": 290200,
      "messageCount": 15,
      "cost": 0.025848500000000003
    },
    {
      "file": "89837295-03df-4c65-88cf-4e4fe708e8bd.jsonl",
      "date": "2026-03-16",
      "inputTokens": 145337,
      "outputTokens": 10580,
      "totalTokens": 1869581,
      "messageCount": 46,
      "cost": 0.0938285
    },
    {
      "file": "28f0605f-74ed-4bc1-a949-3875684389d0.jsonl",
      "date": "2026-03-17",
      "inputTokens": 15662,
      "outputTokens": 1036,
      "totalTokens": 107834,
      "messageCount": 5,
      "cost": 0.009902999999999999
    }
  ],
  "lastUpdated": "2026-03-18T09:54:46.051Z"
}